ucentral/__init__.py
ucentral/cli.py
ucentral/ucentral.py
ucentral/util.py
ucentral-0.0.4.dist-info/METADATA
ucentral-0.0.4.dist-info/WHEEL
ucentral-0.0.4.dist-info/entry_points.txt
ucentral-0.0.4.dist-info/top_level.txt
ucentral-0.0.4.dist-info/RECORD
