Metadata-Version: 2.1
Name: ucentral
Version: 0.0.4
Summary: CLI to create ucentral configuration files
Home-page: https://github.com/aparcar/ucentral-cli
Maintainer: Paul Spooren
Maintainer-email: mail@aparcar.org
License: UNKNOWN
Platform: UNKNOWN
Requires-Dist: click-shell (==2.0)
Requires-Dist: dotty-dict (==1.3.0)
Requires-Dist: jsonschema (==3.2.0)
